psqlpy_sqlalchemy/__init__.py
psqlpy_sqlalchemy/connection.py
psqlpy_sqlalchemy/dbapi.py
psqlpy_sqlalchemy/dialect.py
psqlpy_sqlalchemy-0.1.1b4.dist-info/METADATA
psqlpy_sqlalchemy-0.1.1b4.dist-info/WHEEL
psqlpy_sqlalchemy-0.1.1b4.dist-info/entry_points.txt
psqlpy_sqlalchemy-0.1.1b4.dist-info/top_level.txt
psqlpy_sqlalchemy-0.1.1b4.dist-info/RECORD
