Metadata-Version: 2.4
Name: psqlpy-sqlalchemy
Version: 0.1.1b4
Summary: SQLAlchemy dialect for psqlpy PostgreSQL driver
Author: psqlpy-sqlalchemy contributors
License: MIT
Project-URL: Homepage, https://github.com/h0rn3t/psqlpy-sqlalchemy
Project-URL: Repository, https://github.com/h0rn3t/psqlpy-sqlalchemy
Project-URL: Issues, https://github.com/h0rn3t/psqlpy-sqlalchemy/issues
Keywords: postgresql,psqlpy,sqlalchemy,database,async
Classifier: Development Status :: 3 - Alpha
Classifier: Intended Audience :: Developers
Classifier: License :: OSI Approved :: MIT License
Classifier: Programming Language :: Python :: 3
Classifier: Programming Language :: Python :: 3.10
Classifier: Programming Language :: Python :: 3.11
Classifier: Programming Language :: Python :: 3.12
Classifier: Programming Language :: Python :: 3.13
Classifier: Programming Language :: Python :: 3.14
Classifier: Topic :: Database
Classifier: Topic :: Software Development :: Libraries :: Python Modules
Requires-Python: >=3.10
Requires-Dist: sqlalchemy>=2.0.0
Requires-Dist: psqlpy>=0.11.0
Provides-Extra: dev
Requires-Dist: pytest>=7.0.0; extra == "dev"
Requires-Dist: pytest-asyncio>=0.21.0; extra == "dev"
Requires-Dist: greenlet>=1.0.0; extra == "dev"
Requires-Dist: ruff>=0.1.0; extra == "dev"
Requires-Dist: mypy>=1.0.0; extra == "dev"
Requires-Dist: sqlmodel>=0.0.14; extra == "dev"
Requires-Dist: pytest-cov; extra == "dev"
Requires-Dist: fastapi>=0.68.0; extra == "dev"
Requires-Dist: starlette>=0.14.0; extra == "dev"
Requires-Dist: fastapi-async-sqlalchemy>=0.3.0; extra == "dev"
Requires-Dist: asyncpg>=0.28.0; extra == "dev"
Provides-Extra: fastapi
Requires-Dist: fastapi>=0.68.0; extra == "fastapi"
Requires-Dist: starlette>=0.14.0; extra == "fastapi"
